ntn/__init__.py
ntn/__main__.py
ntn/agent.py
ntn/cli.py
ntn/config.py
ntn/config.yaml
ntn/docker_manager.py
ntn/prompts.py
ntn/provider_types.py
ntn/providers.py
ntn/session_log.py
ntn/stream_accumulator.py
ntn/test_cache.py
ntn/tool_exec.py
ntn/tools.py
ntn/ui.py
ntn/_version.py
ntn-0.3.6.dist-info/METADATA
ntn-0.3.6.dist-info/WHEEL
ntn-0.3.6.dist-info/entry_points.txt
ntn-0.3.6.dist-info/licenses/LICENSE
ntn-0.3.6.dist-info/RECORD
