Metadata-Version: 2.4
Name: ntn
Version: 0.3.6
Summary: Minimal AI coding agent
Project-URL: Homepage, https://github.com/ntrnghia/coding-agent
Project-URL: Repository, https://github.com/ntrnghia/coding-agent
Project-URL: Issues, https://github.com/ntrnghia/coding-agent/issues
Author-email: NTN <ntn@example.com>
License-Expression: MIT
License-File: LICENSE
Keywords: agent,ai,anthropic,assistant,claude,coding,gpt,openai
Classifier: Development Status :: 4 - Beta
Classifier: Environment :: Console
Classifier: Intended Audience :: Developers
Classifier: License :: OSI Approved :: MIT License
Classifier: Operating System :: OS Independent
Classifier: Programming Language :: Python :: 3
Classifier: Programming Language :: Python :: 3.10
Classifier: Programming Language :: Python :: 3.11
Classifier: Programming Language :: Python :: 3.12
Classifier: Topic :: Software Development
Classifier: Topic :: Software Development :: Code Generators
Requires-Python: >=3.10
Requires-Dist: anthropic>=0.75.0
Requires-Dist: beautifulsoup4>=4.12.0
Requires-Dist: colorama>=0.4.6
Requires-Dist: ddgs>=6.0.0
Requires-Dist: openai>=1.12.0
Requires-Dist: prompt-toolkit>=3.0.0
Requires-Dist: pyyaml>=6.0
Requires-Dist: requests>=2.31.0
Requires-Dist: tiktoken>=0.5.0
Provides-Extra: dev
Requires-Dist: black>=23.0.0; extra == 'dev'
Requires-Dist: pytest>=7.0.0; extra == 'dev'
Requires-Dist: ruff>=0.1.0; extra == 'dev'
